{"json_modified": "2016-11-15T14:15:36.361581", "uuid": "b5fec298-7739-421a-9b60-2689454e8910", "title": "Cookie", "url": "/en-US/docs/Web/HTTP/Headers/Cookie", "tags": ["Cookies", "Reference", "cookies", "HTTP", "request", "header"], "translations": [{"uuid": "78c6d533-9ef1-4313-90c9-ead5eb25f6b7", "title": "Cookie", "url": "/ko/docs/Web/HTTP/Headers/Cookie", "tags": [], "summary": "<strong><code>Cookie</code></strong> HTTP \uc694\uccad \ud5e4\ub354\ub294 <a href=\"/ko/docs/Web/HTTP/Headers/Set-Cookie\" title=\"The documentation about this has not yet been written; please consider contributing!\"><code>Set-Cookie</code></a> \ud5e4\ub354\uc640 \ud568\uaed8 \uc11c\ubc84\uc5d0 \uc758\ud574 \uc774\uc804\uc5d0 \uc804\uc1a1\ub418\uc5b4 \uc800\uc7a5\ub41c <a href=\"/en-US/docs/Web/HTTP/Cookies\">HTTP cookies</a>\ub97c \ud3ec\ud568\ud569\ub2c8\ub2e4.", "localization_tags": ["inprogress"], "locale": "ko", "last_edit": "2016-11-07T01:18:32", "review_tags": []}], "modified": "2016-11-15T14:15:36", "label": "Cookie", "localization_tags": [], "locale": "en-US", "id": 193189, "last_edit": "2016-11-15T14:15:31", "summary": "The <strong><code>Cookie</code></strong> HTTP request header contains stored <a href=\"/en-US/docs/Web/HTTP/Cookies\">HTTP cookies</a> previously sent by the server with the <a href=\"/en-US/docs/Web/HTTP/Headers/Set-Cookie\" title=\"The Set-Cookie HTTP response header is used to send cookies from the server to the user agent.\"><code>Set-Cookie</code></a> header.", "sections": [{"id": "Quick_Links", "title": null}, {"id": "Syntax", "title": "Syntax"}, {"id": "Examples", "title": "Examples"}, {"id": "Specifications", "title": "Specifications"}, {"id": "Browser_compatibility", "title": "Browser compatibility"}, {"id": "See_also", "title": "See also"}], "slug": "Web/HTTP/Headers/Cookie", "review_tags": []}